rebotics_scripts-19.5.5.dist-info/METADATA
rebotics_scripts-19.5.5.dist-info/RECORD
rebotics_scripts-19.5.5.dist-info/WHEEL
rebotics_scripts-19.5.5.dist-info/entry_points.txt
rebotics_scripts-19.5.5.dist-info/top_level.txt
scripts/__init__.py
scripts/admin_api_client.py
scripts/api_v4_client.py
scripts/cli.py
scripts/dataset_api_client.py
scripts/renderer.py
scripts/retailer_api_client.py
scripts/upcitemdb_interface.py
scripts/utils.py
sdk/__init__.py
sdk/utils.py
sdk/providers/__init__.py
sdk/providers/admin.py
sdk/providers/base.py
sdk/providers/dataset.py
sdk/providers/facenet.py
sdk/providers/object_detection.py
sdk/providers/retailer.py
