Metadata-Version: 2.1
Name: rebotics-scripts
Version: 19.5.5
Summary: Collection of scripts for rebotics
Home-page: http://retechlabs.com/
Author: Malik Sulaimanov
Author-email: malik@retechlabs.com
License: BSD
Platform: any
Classifier: Development Status :: 4 - Beta
Classifier: Environment :: Console
Classifier: Intended Audience :: Developers
Classifier: License :: OSI Approved :: BSD License
Classifier: Operating System :: POSIX
Classifier: Operating System :: MacOS
Classifier: Operating System :: Unix
Classifier: Operating System :: Microsoft :: Windows
Classifier: Programming Language :: Python
Classifier: Programming Language :: Python :: 2
Classifier: Programming Language :: Python :: 3
Requires-Dist: click (>=7.0)
Requires-Dist: ffmpeg-python (==0.1.17)
Requires-Dist: numpy (==1.16.2)
Requires-Dist: requests (==2.21.0)
Requires-Dist: PySocks (!=1.5.7,>=1.5.6)
Requires-Dist: requests[socks]
Requires-Dist: requests-toolbelt (==0.9.1)
Requires-Dist: tqdm (==4.31.1)
Requires-Dist: xlrd (==1.2.0)
Requires-Dist: six (==1.12.0)
Requires-Dist: pytz
Requires-Dist: ptable
Requires-Dist: python-dateutil
Requires-Dist: humanize
